nonebot_plugin_ocr/__init__.py
nonebot_plugin_ocr/bot/bot_manage.py
nonebot_plugin_ocr/bot/onebot11.py
nonebot_plugin_ocr/bot/tool.py
nonebot_plugin_ocr/config.py
nonebot_plugin_ocr/ocr/baidu_cloud.py
nonebot_plugin_ocr/ocr/client.py
nonebot_plugin_ocr/ocr/ocr_init.py
nonebot_plugin_ocr-0.3.2.dist-info/WHEEL
nonebot_plugin_ocr-0.3.2.dist-info/METADATA
nonebot_plugin_ocr-0.3.2.dist-info/RECORD
