Metadata-Version: 2.1
Name: nonebot-plugin-ocr
Version: 0.3.2
Summary: OCR plugin for nonebot2
Home-page: https://github.com/NewYearPrism/nonebot-plugin-ocr
License: MIT
Keywords: nonebot,nonebot2
Author: NewYearPrism
Maintainer: NewYearPrism
Requires-Python: >=3.10,<4.0
Classifier: License :: OSI Approved :: MIT License
Classifier: Programming Language :: Python :: 3
Classifier: Programming Language :: Python :: 3.10
Requires-Dist: diskcache (>=5.4.0,<6.0.0)
Requires-Dist: httpx (>=0.23.0,<0.24.0)
Requires-Dist: nonebot-adapter-onebot (>=2.1.3,<3.0.0)
Requires-Dist: nonebot2 (>=2.0.0-beta.5,<3.0.0)
Requires-Dist: tomli (>=2.0.1,<3.0.0)
